mhmixtools/__init__.py
mhmixtools/decorators.py
mhmixtools/folder_structure_generator.py
mhmixtools/image_utils.py
mhmixtools/template_sync.py
mhmixtools/webcrawler.py
mhmixtools-0.2.0.dist-info/licenses/LICENCE
mhmixtools-0.2.0.dist-info/METADATA
mhmixtools-0.2.0.dist-info/WHEEL
mhmixtools-0.2.0.dist-info/top_level.txt
mhmixtools-0.2.0.dist-info/RECORD
