Metadata-Version: 2.4
Name: mhmixtools
Version: 0.2.0
Summary: This package contains various automotion tools
Home-page: https://github.com/mahamudh472/mhmixtools.git
Author: Md. Mahmud Hasan
Author-email: mahadymahamudh472@gmail.com
License: MIT
Classifier: Programming Language :: Python :: 3
Classifier: License :: OSI Approved :: MIT License
Classifier: Operating System :: OS Independent
License-File: LICENCE
Requires-Dist: requests
Requires-Dist: bs4
Requires-Dist: pillow
Dynamic: author
Dynamic: author-email
Dynamic: classifier
Dynamic: description
Dynamic: description-content-type
Dynamic: home-page
Dynamic: license
Dynamic: license-file
Dynamic: requires-dist
Dynamic: summary
